opendss_scivis/TeX_code.py
opendss_scivis/__init__.py
opendss_scivis/add_line_legend.py
opendss_scivis/add_marker_legend.py
opendss_scivis/colname_stats.py
opendss_scivis/colname_stats2.py
opendss_scivis/compare_csv_files.py
opendss_scivis/compare_directory.py
opendss_scivis/file_stats.py
opendss_scivis/get_file_directory.py
opendss_scivis/get_files_in_directory.py
opendss_scivis/get_time_series.py
opendss_scivis/get_time_series_axes.py
opendss_scivis/get_time_series_axes_old.py
opendss_scivis/get_time_series_plot_options.py
opendss_scivis/is_list_of_strings.py
opendss_scivis/plot_xy.py
opendss_scivis/plot_xy_axes.py
opendss_scivis/plot_xy_line.py
opendss_scivis/plot_xy_markers.py
opendss_scivis/read_element_data.py
opendss_scivis/read_element_data_old.py
opendss_scivis/scalar_map.py
opendss_scivis/time_series_plot.py
opendss_scivis/time_series_plot2.py
OpenDSS_SciVis-1.1.1.dist-info/METADATA
OpenDSS_SciVis-1.1.1.dist-info/WHEEL
OpenDSS_SciVis-1.1.1.dist-info/top_level.txt
OpenDSS_SciVis-1.1.1.dist-info/RECORD
