Metadata-Version: 2.1
Name: OpenDSS-SciVis
Version: 1.1.1
Summary: A Python package for analysis and visualization of data produced by the OpenDSS software application.
Home-page: https://github.com/PeterRochford/OpenDSS_SciVis/tree/main
Author: Peter Rochford
Author-email: peter.rochford@xatorcorp.com
Classifier: Development Status :: 3 - Alpha
Classifier: Intended Audience :: Developers
Classifier: License :: OSI Approved :: MIT License
Classifier: Programming Language :: Python :: 3.11
Requires-Dist: matplotlib
Requires-Dist: numpy
Requires-Dist: pandas
Requires-Dist: scipy
Requires-Dist: SkillMetrics
